LICENSE
README.rst
setup.py
cukoo_fastapi_addto/__init__.py
cukoo_fastapi_addto.egg-info/PKG-INFO
cukoo_fastapi_addto.egg-info/SOURCES.txt
cukoo_fastapi_addto.egg-info/dependency_links.txt
cukoo_fastapi_addto.egg-info/requires.txt
cukoo_fastapi_addto.egg-info/top_level.txt
cukoo_fastapi_addto/adapter/__init__.py
cukoo_fastapi_addto/adapter/message/__init__.py
cukoo_fastapi_addto/adapter/message/kafka.py
cukoo_fastapi_addto/adapter/message/rabbitmq.py
cukoo_fastapi_addto/adapter/message/redis.py
cukoo_fastapi_addto/framework/__init__.py
cukoo_fastapi_addto/framework/base_model.py
cukoo_fastapi_addto/framework/base_repository.py
cukoo_fastapi_addto/framework/base_schema.py
cukoo_fastapi_addto/framework/custom_exception.py
cukoo_fastapi_addto/framework/database.py
cukoo_fastapi_addto/framework/dependencies.py
cukoo_fastapi_addto/framework/exception.py
cukoo_fastapi_addto/framework/logger.py
cukoo_fastapi_addto/framework/response_model.py
cukoo_fastapi_addto/framework/security.py